qaviton_monitors/__init__.py
qaviton_monitors/log.py
qaviton_monitors/simple_monitor.py
qaviton_monitors-2019.11.15.20.45.47.498787.dist-info/LICENSE
qaviton_monitors-2019.11.15.20.45.47.498787.dist-info/METADATA
qaviton_monitors-2019.11.15.20.45.47.498787.dist-info/WHEEL
qaviton_monitors-2019.11.15.20.45.47.498787.dist-info/top_level.txt
qaviton_monitors-2019.11.15.20.45.47.498787.dist-info/RECORD
