Metadata-Version: 2.1
Name: qaviton-monitors
Version: 2019.11.15.20.45.47.498787
Summary: qaviton monitors
Home-page: https://github.com/qaviton/qaviton_monitors
Author: yehonadav
Author-email: yonadav.barilan@gmail.com
License: apache-2.0
Platform: UNKNOWN
Classifier: Programming Language :: Python :: 3.6
Requires-Dist: psutil (>=5.6.3)
Requires-Dist: threaders (>=0.2.13)
